pymtcnn/__init__.py
pymtcnn/base.py
pymtcnn/cpp_cnn_loader_optimized.py
pymtcnn/detector.py
pymtcnn/backends/__init__.py
pymtcnn/backends/coreml_backend.py
pymtcnn/backends/onnx_backend.py
pymtcnn/models/onet.onnx
pymtcnn/models/pnet.onnx
pymtcnn/models/rnet.onnx
pymtcnn/models/onet_fp32.mlpackage/Manifest.json
pymtcnn/models/onet_fp32.mlpackage/Data/com.apple.CoreML/model.mlmodel
pymtcnn/models/onet_fp32.mlpackage/Data/com.apple.CoreML/weights/weight.bin
pymtcnn/models/pnet_fp32.mlpackage/Manifest.json
pymtcnn/models/pnet_fp32.mlpackage/Data/com.apple.CoreML/model.mlmodel
pymtcnn/models/pnet_fp32.mlpackage/Data/com.apple.CoreML/weights/weight.bin
pymtcnn/models/rnet_fp32.mlpackage/Manifest.json
pymtcnn/models/rnet_fp32.mlpackage/Data/com.apple.CoreML/model.mlmodel
pymtcnn/models/rnet_fp32.mlpackage/Data/com.apple.CoreML/weights/weight.bin
pymtcnn-1.1.3.dist-info/licenses/LICENSE
pymtcnn-1.1.3.dist-info/METADATA
pymtcnn-1.1.3.dist-info/WHEEL
pymtcnn-1.1.3.dist-info/top_level.txt
pymtcnn-1.1.3.dist-info/RECORD
